{
  "3121101183": {
    "nama": "Dicky Mulia Fiqri",
    "pass": "stikom",
    "prodi": "D3 Manajemen Informatika",
    "hobi": "Listening to music",
    "credit": "Rp. 7.000.000.000"
  },

  "3121101184": {
    "nama": "Damara Laedy Meilanda",
    "pass": "stikom",
    "prodi": "S1 Manajemen Informatika",
    "hobi": "Make over",
    "credit": "Rp. 5.000.000.000"
  },

  "3121101185": {
    "nama": "Dewi Alfina",
    "pass": "stikom",
    "prodi": "D3 Manajemen Informatika",
    "hobi": "Sell and buy",
    "credit": "Rp. 10.000.000.000"
  }
}
